{
    "swagger": "2.0",
    "info": {
        "title": "Your API",
        "version": "1.0.0"
    },
    "paths": {
        "/api/users": {
            "get": {
                "summary": "Get a list of users",
                "responses": {
                    "200": {
                        "description": "Successful response",
                        "schema": {
                            "type": "array",
                            "items": {
                                "$ref": "#/definitions/User"
                            }
                        }
                    }
                }
            }
        }
    },
    "definitions": {
        "User": {
            "type": "object",
            "properties": {
                "id": {
                    "type": "integer"
                },
                "name": {
                    "type": "string"
                }
            }
        }
    }
}